{
  "group": "natureplus",
  "type": "minecraft:crafting_shaped",
  "pattern": [
    "012",
    "345"
  ],
  "key": {
    "0": {
      "item": "natureplus:plant_stem"
    },
    "1": {
      "item": "natureplus:plant_stem"
    },
    "2": {
      "item": "natureplus:plant_stem"
    },
    "3": {
      "item": "natureplus:plant_stem"
    },
    "4": {
      "item": "natureplus:plant_stem"
    },
    "5": {
      "item": "natureplus:plant_stem"
    }
  },
  "result": {
    "item": "natureplus:plant_stem_wall",
    "count": 6
  }
}